macro_embedding_flow-0.0.2.dist-info/licenses/LICENCE
macro_embeddings_flow/__init__.py
macro_embeddings_flow/main.py
macro_embeddings_flow/contracts/__init__.py
macro_embeddings_flow/contracts/contractsChunks.py
macro_embeddings_flow/extract/__init__.py
macro_embeddings_flow/extract/extract.py
macro_embeddings_flow/load/__init__.py
macro_embeddings_flow/load/load.py
macro_embeddings_flow/transform/__init__.py
macro_embeddings_flow/transform/transform.py
macro_embedding_flow-0.0.2.dist-info/METADATA
macro_embedding_flow-0.0.2.dist-info/WHEEL
macro_embedding_flow-0.0.2.dist-info/entry_points.txt
macro_embedding_flow-0.0.2.dist-info/top_level.txt
macro_embedding_flow-0.0.2.dist-info/RECORD
