Metadata-Version: 2.4
Name: macro-embedding-flow
Version: 0.0.2
Summary: ETL Para banco macro, transforma los chunks de pdf bancarios y los tranforma en embeddings de 768 dimenciones y la sube a s3
Home-page: https://github.com/facuvegaingenieer/macro-embedding-flow
Author: Walter Facundo Vega
Author-email: facundo.vega1234@gmail.com
License: MIT
Classifier: Programming Language :: Python :: 3
Classifier: Programming Language :: Python :: 3.8
Classifier: License :: OSI Approved :: MIT License
Classifier: Operating System :: OS Independent
Requires-Python: >=3.8
License-File: LICENCE
Requires-Dist: torch==2.8.0
Requires-Dist: sentence-transformers
Requires-Dist: transformers
Requires-Dist: boto3
Requires-Dist: pandas
Requires-Dist: pyarrow
Requires-Dist: python-dotenv
Dynamic: author
Dynamic: author-email
Dynamic: classifier
Dynamic: description
Dynamic: description-content-type
Dynamic: home-page
Dynamic: license
Dynamic: license-file
Dynamic: requires-dist
Dynamic: requires-python
Dynamic: summary
